{
  "_class": "group",
  "do_objectID": "0E17E0F8-431D-40F7-B720-33FEDB7C1F92",
  "exportOptions": {
    "_class": "exportOptions",
    "exportFormats": [
    ],
    "includedLayerIds": [
    ],
    "layerOptions": 0,
    "shouldTrim": false
  },
  "frame": {
    "_class": "rect",
    "constrainProportions": false,
    "height": 16,
    "width": 26,
    "x": 0,
    "y": 3
  },
  "hasClickThrough": false,
  "isFlippedHorizontal": false,
  "isFlippedVertical": false,
  "isLocked": false,
  "isVisible": true,
  "layerListExpandedType": 0,
  "layers": [
    {
      "class": "shapeGroup",
      "id": "0A0F5C60-DC56-4167-A4DA-08B1C97C4255"
    },
    {
      "class": "shapeGroup",
      "id": "3646820C-A2D4-445D-9D81-B70C8A129301"
    }
  ],
  "name": "Group",
  "nameIsFixed": false,
  "originalObjectID": "0E17E0F8-431D-40F7-B720-33FEDB7C1F92",
  "resizingConstraint": 9,
  "resizingType": 0,
  "rotation": 0,
  "shouldBreakMaskChain": false,
  "style": {
    "_class": "style",
    "endDecorationType": 0,
    "miterLimit": 10,
    "startDecorationType": 0
  },
  "userInfo": {
    "com.animaapp.stc-sketch-plugin": {
      "kModelPropertiesKey": {
      }
    }
  }
}