{
  "_class": "group",
  "do_objectID": "594D8F84-4963-47AD-8FC4-FF110F2D3FCE",
  "exportOptions": {
    "_class": "exportOptions",
    "exportFormats": [
    ],
    "includedLayerIds": [
    ],
    "layerOptions": 0,
    "shouldTrim": false
  },
  "frame": {
    "_class": "rect",
    "constrainProportions": false,
    "height": 80,
    "width": 350,
    "x": 0,
    "y": 0
  },
  "hasClickThrough": false,
  "isFlippedHorizontal": false,
  "isFlippedVertical": false,
  "isLocked": false,
  "isVisible": true,
  "layerListExpandedType": 0,
  "layers": [
    {
      "class": "shapeGroup",
      "id": "8C76A224-C5F0-4C28-8FBC-6F73190A1A2A"
    },
    {
      "class": "text",
      "id": "10E810A8-EE51-4796-B648-76DA962AE393"
    },
    {
      "class": "shapeGroup",
      "id": "1855EC8C-0E13-4D33-90F5-7BB2F384CD24"
    }
  ],
  "name": "Forms/On Dark/Text Area/Small/Focus",
  "nameIsFixed": true,
  "originalObjectID": "594D8F84-4963-47AD-8FC4-FF110F2D3FCE",
  "resizingConstraint": 63,
  "resizingType": 0,
  "rotation": 0,
  "shouldBreakMaskChain": false,
  "style": {
    "_class": "style",
    "endDecorationType": 0,
    "miterLimit": 10,
    "startDecorationType": 0
  },
  "userInfo": {
    "com.animaapp.stc-sketch-plugin": {
      "kModelPropertiesKey": {
      }
    }
  }
}