{
  "_class": "group",
  "do_objectID": "E454A9D3-D917-4A2A-8BE0-2AA4464B1C45",
  "exportOptions": {
    "_class": "exportOptions",
    "exportFormats": [
    ],
    "includedLayerIds": [
    ],
    "layerOptions": 0,
    "shouldTrim": false
  },
  "frame": {
    "_class": "rect",
    "constrainProportions": false,
    "height": 29,
    "width": 99,
    "x": 0,
    "y": 0
  },
  "hasClickThrough": false,
  "isFlippedHorizontal": false,
  "isFlippedVertical": false,
  "isLocked": false,
  "isVisible": true,
  "layerListExpandedType": 0,
  "layers": [
    {
      "class": "shapeGroup",
      "id": "BFD40253-BF88-4969-9B4C-66939ABAA044"
    },
    {
      "class": "text",
      "id": "8F75848D-B031-46AE-AFD1-BA8CAB0F93C2"
    }
  ],
  "name": "Button Groups/On Light/Medium/Middle/Active",
  "nameIsFixed": true,
  "originalObjectID": "E454A9D3-D917-4A2A-8BE0-2AA4464B1C45",
  "resizingConstraint": 63,
  "resizingType": 0,
  "rotation": 0,
  "shouldBreakMaskChain": false,
  "style": {
    "_class": "style",
    "endDecorationType": 0,
    "miterLimit": 10,
    "startDecorationType": 0
  },
  "userInfo": {
    "com.animaapp.stc-sketch-plugin": {
      "kModelPropertiesKey": {
      }
    }
  }
}