{
  "_class": "group",
  "do_objectID": "FA78F006-827F-48E1-97E8-A04084D1698B",
  "exportOptions": {
    "_class": "exportOptions",
    "exportFormats": [
    ],
    "includedLayerIds": [
    ],
    "layerOptions": 0,
    "shouldTrim": false
  },
  "frame": {
    "_class": "rect",
    "constrainProportions": false,
    "height": 19,
    "width": 19,
    "x": 91,
    "y": 0
  },
  "hasClickThrough": false,
  "isFlippedHorizontal": false,
  "isFlippedVertical": false,
  "isLocked": false,
  "isVisible": true,
  "layerListExpandedType": 0,
  "layers": [
    {
      "class": "shapeGroup",
      "id": "137DC88D-A31C-48D2-8C41-263EA88B44C0"
    }
  ],
  "name": "Containers/Tooltip/Edge Carat",
  "nameIsFixed": false,
  "originalObjectID": "FA78F006-827F-48E1-97E8-A04084D1698B",
  "resizingConstraint": 13,
  "resizingType": 0,
  "rotation": 0,
  "shouldBreakMaskChain": false,
  "style": {
    "_class": "style",
    "endDecorationType": 0,
    "miterLimit": 10,
    "startDecorationType": 0
  },
  "userInfo": {
    "com.animaapp.stc-sketch-plugin": {
      "kModelPropertiesKey": {
      }
    }
  }
}