{
  "_class": "group",
  "do_objectID": "C5096EF4-9EE2-444A-802A-936C0576046A",
  "exportOptions": {
    "_class": "exportOptions",
    "exportFormats": [
    ],
    "includedLayerIds": [
    ],
    "layerOptions": 0,
    "shouldTrim": false
  },
  "frame": {
    "_class": "rect",
    "constrainProportions": false,
    "height": 23,
    "width": 200,
    "x": 0,
    "y": 0
  },
  "hasClickThrough": false,
  "isFlippedHorizontal": false,
  "isFlippedVertical": false,
  "isLocked": false,
  "isVisible": true,
  "layerListExpandedType": 0,
  "layers": [
    {
      "class": "shapeGroup",
      "id": "08DD5FD4-97AC-488E-A095-541EA1BD2C33"
    },
    {
      "class": "text",
      "id": "13FEFFF5-4CAD-4674-B389-ECDE36306ED7"
    },
    {
      "class": "shapeGroup",
      "id": "E8B3FE42-EBB1-4C7A-9BA3-861079760533"
    }
  ],
  "name": "Forms/On Light/Text Box/Small/Default",
  "nameIsFixed": true,
  "originalObjectID": "C5096EF4-9EE2-444A-802A-936C0576046A",
  "resizingConstraint": 63,
  "resizingType": 0,
  "rotation": 0,
  "shouldBreakMaskChain": false,
  "style": {
    "_class": "style",
    "endDecorationType": 0,
    "miterLimit": 10,
    "startDecorationType": 0
  },
  "userInfo": {
    "com.animaapp.stc-sketch-plugin": {
      "kModelPropertiesKey": {
      }
    }
  }
}